{
  "chassis": "E70",
  "module": "Car information computer (CIC)",
  "sgbd": "CICR",
  "scheme": "code",
  "faults": {
    "C508": "Head-unit to diversity connection: open circuit",
    "C509": "Head-unit to diversity connection: short to B+",
    "C50A": "Head-unit to diversity connection: short to ground",
    "C50C": "Diversity to antennas connection: open circuit",
    "C50D": "Head-unit to DAB L-band antenna base: open circuit",
    "C50F": "Head-unit to DAB L-band antenna base: short circuit",
    "C511": "Head-unit to DAB Band III antenna base: open circuit",
    "C513": "Head-unit to DAB Band III antenna base: short circuit",
    "C5AE": "Head-unit to SDARS antenna base: open circuit",
    "C5AF": "Head-unit to SDARS antenna base: short circuit",
    "C5B0": "SDARS module: security sector was erased",
    "C517": "Head-unit to GPS antenna base: open circuit",
    "C518": "Head-unit to GPS antenna base: short to B+",
    "C519": "Head-unit to GPS antenna base: short to ground",
    "C51D": "Head-unit to VICS beacon antenna base: open circuit",
    "C51E": "Head-unit to VICS beacon antenna base: short circuit",
    "C51F": "GPS receiver: defective",
    "C5AC": "GPS receiver: firmware fault",
    "C520": "Gyro: defective",
    "C521": "Acceleration sensor: defective",
    "C522": "HDD map data: not available",
    "C523": "HDD map data: not readable at all",
    "C524": "HDD map data: corrupt",
    "C525": "DVD map data: not available",
    "C526": "DVD map data: not readable at all",
    "C527": "DVD map data: corrupt",
    "C528": "DVD map data: time-consuming read errors",
    "C529": "No GPS reception in the last 20 kilometers",
    "C52A": "Positioning not possible over TBD time window",
    "E1E0": "Wheel rotational speed signal: not present",
    "E1E1": "Wheel rotational speed signal: implausible",
    "E1E2": "Reverse gear signal: implausible",
    "E1E3": "Reverse gear signal: not present",
    "C52F": "Internal horizontal travel direction signal: implausible",
    "E1E4": "External horizontal travel direction signal: implausible",
    "E1E5": "External horizontal travel direction signal: not present",
    "E1E6": "External vertical travel direction signal: implausible",
    "E1E7": "External vertical travel direction signal: not present",
    "C535": "Route/trip memory area on HDD: corrupt",
    "C536": "My POI memory area on HDD: corrupt",
    "C537": "Destinations memory area on HDD: corrupt",
    "C538": "Address book memory area on HDD: corrupt",
    "C53A": "Calculation fault from navigation computer",
    "E1E8": "Odometer signal: implausible",
    "C53F": "Top-HiFi amplifier communication fault",
    "C540": "Speaker output wires front left: open circuit",
    "C541": "Speaker output wires front left: short to B+",
    "C542": "Speaker output wires front left: short to ground",
    "C543": "Speaker output wires front left: short between the 2 wires",
    "C544": "Speaker output wires front right: open circuit",
    "C545": "Speaker output wires front right: short to B+",
    "C546": "Speaker output wires front right: short to ground",
    "C547": "Speaker output wires front right: short between the 2 wires",
    "C548": "Speaker output wires rear left: open circuit",
    "C549": "Speaker output wires rear left: short to B+",
    "C54A": "Speaker output wires rear left: short to ground",
    "C54B": "Speaker output wires rear left: short between the 2 wires",
    "C54C": "Speaker output wires rear right: open circuit",
    "C54D": "Speaker output wires rear right: short to B+",
    "C54E": "Speaker output wires rear right: short to ground",
    "C54F": "Speaker output wires rear right: short between the 2 wires",
    "C560": "FBAS input 1: no video or sync signal present",
    "C561": "FBAS input 2: no video or sync signal present",
    "C562": "FBAS input 3: no video or sync signal present",
    "C563": "FBAS input 1: signal out of tolerance",
    "C564": "FBAS input 2: signal out of tolerance",
    "C565": "FBAS input 3: signal out of tolerance",
    "C568": "RAD ON line: short to B+",
    "C569": "RAD ON line: short to ground",
    "C56C": "Video watchdog was triggered",
    "C5AA": "Video link: no/invalid coding data for source %s to sink %s; not established",
    "C5AB": "Video link: video switch %i fault connecting source %s to sink %s; failed",
    "C56D": "Head-unit to microphone 1 connection: open circuit",
    "C56E": "Head-unit to microphone 1 connection: short to B+",
    "C56F": "Head-unit to microphone 1 connection: short to ground",
    "C573": "Hard disk drive hardware fault",
    "C576": "DVD drive hardware fault",
    "C579": "DVD medium fault",
    "C57A": "ATC test negative: DVD drive defective",
    "E1E9": "Failure of the front screen",
    "C57F": "FB communication fault",
    "C580": "FB hardware fault",
    "C581": "No response from ETC module to request messages",
    "C583": "Fan fault",
    "C585": "Internal temperature fault",
    "C587": "Sleep mode of the gateway is prevented",
    "C588": "External undervoltage",
    "C589": "External overvoltage",
    "E1CC": "Device did not accept/confirm monitoring message (Error_Monitoring)",
    "E1CD": "Waking device failed 3x to wake network (Error_WakeUp_Failed)",
    "E1CE": "Despite Shutdown(Execute) light did not go off (Error_Light_Not_Off)",
    "E1CF": "Central registry does not match target config (Error_Registry_New)",
    "E1D0": "Ring break diagnosis was performed (Error_Ring_Diagnose)",
    "E1D2": "A device shut down due to over-temperature (Error_Temp_Shutdown)",
    "E1C4": "K-CAN wiring fault",
    "E1C7": "K-CAN communication fault",
    "C58A": "Flash Ethernet connection: link status from Ethernet driver not OK",
    "C58C": "USB-VBUS head-unit to USB user interface: short to ground",
    "C58D": "Running PIA sequence aborted due to vehicle state change",
    "C58E": "Signature of porting file to import is corrupt",
    "C58F": "File structure of porting file to import is corrupt",
    "C590": "Version of porting file to import is unknown",
    "C591": "Running PIA sequence aborted by user interaction",
    "C592": "PIA software fault",
    "C593": "Not enough memory on external storage medium",
    "C594": "Fault writing to external storage medium",
    "C595": "Fault reading from external storage medium",
    "E1EB": "Head unit did not receive radio-key status telegram from CAS",
    "C597": "Radio-key status telegram from CAS lacks profile number requested",
    "C598": "Installed PIA function did not answer request for its setting value",
    "C599": "PIA function not found at config request sent a setting value",
    "C59A": "Installed PIA function did not confirm setting of its value",
    "C59B": "PIA function reported config info without being requested",
    "C59C": "PIA function delivers corrupt configuration information",
    "C59D": "Multiple telegrams with differing config info for one PIA-ID",
    "C59E": "PIA function current profile number differs from head unit record",
    "C59F": "Coding fault work area",
    "C5A0": "Coding fault master area",
    "C5A1": "Mainboard hardware fault",
    "C5A2": "Flash file system faulty",
    "C5A3": "Serious software fault: reflash software",
    "C5B9": "Loading of vehicle-specific graphics failed",
    "C5BA": "HDD safe mode active",
    "C5BF": "SDARS module not active",
    "10E0": "Error_Software_Fault",
    "E1EA": "PDC signal: implausible",
    "FFFF": "Unknown fault location"
  }
}